README.txt
setup.py
pydataframe/__init__.py
pydataframe/dataframe.py
pydataframe/factors.py
pydataframe/parsers.py
pydataframe/r_tests.py
pydataframe/tests.py
pydataframe.egg-info/PKG-INFO
pydataframe.egg-info/SOURCES.txt
pydataframe.egg-info/dependency_links.txt
pydataframe.egg-info/requires.txt
pydataframe.egg-info/top_level.txt