Metadata-Version: 1.0
Name: pydataframe
Version: 0.1.5
Summary: UNKNOWN
Home-page: http://code.google.com/p/pydataframe/
Author: Florian Finkernagel
Author-email: finkernagel@coonabibba.de
License: BSD
Platform: UNKNOWN
